python_test_video_async/__init__.py
python_test_video_async/api.py
python_test_video_async/client.py
python_test_video_async/exceptions.py
python_test_video_async/live_streams.py
python_test_video_async/media.py
python_test_video_async/playback_ids.py
python_test_video_async/signing_keys.py
python_test_video_async-1.0.0.dist-info/METADATA
python_test_video_async-1.0.0.dist-info/WHEEL
python_test_video_async-1.0.0.dist-info/top_level.txt
python_test_video_async-1.0.0.dist-info/RECORD
